vizro_mcp/__init__.py
vizro_mcp/py.typed
vizro_mcp/server.py
vizro_mcp/_schemas/__init__.py
vizro_mcp/_schemas/schemas.py
vizro_mcp/_utils/__init__.py
vizro_mcp/_utils/configs.py
vizro_mcp/_utils/prompts.py
vizro_mcp/_utils/utils.py
iflow_mcp_vizro_mcp-0.1.2.dist-info/METADATA
iflow_mcp_vizro_mcp-0.1.2.dist-info/WHEEL
iflow_mcp_vizro_mcp-0.1.2.dist-info/entry_points.txt
iflow_mcp_vizro_mcp-0.1.2.dist-info/licenses/LICENSE.txt
iflow_mcp_vizro_mcp-0.1.2.dist-info/RECORD
