Metadata-Version: 2.4
Name: iflow-mcp_vizro-mcp
Version: 0.1.2
Summary: MCP server to help create Vizro dashboards and charts
Author: Vizro Team
License-File: LICENSE.txt
Classifier: Programming Language :: Python
Classifier: Programming Language :: Python :: 3.10
Classifier: Programming Language :: Python :: 3.11
Classifier: Programming Language :: Python :: 3.12
Classifier: Programming Language :: Python :: 3.13
Requires-Python: >=3.10
Requires-Dist: click>=8.1.7
Requires-Dist: httpx>=0.28.1
Requires-Dist: mcp[cli]>=1.6.0
Requires-Dist: pandas[excel,html,parquet]
Requires-Dist: vizro>=0.1.45
